presenturpy/__init__.py
presenturpy/misc.py
presenturpy/presentation.py
presenturpy/slide.py
presenturpy-0.0.0.dist-info/METADATA
presenturpy-0.0.0.dist-info/WHEEL
presenturpy-0.0.0.dist-info/top_level.txt
presenturpy-0.0.0.dist-info/RECORD
