Metadata-Version: 2.1
Name: presenturpy
Version: 0.0.0
Summary: Python right-in-your-terminal presentation maker (sorta)
Author-email: theammir <the@ammir.dev>, valsoray-dev <me@valsoray.dev>
License: MIT License
Project-URL: Homepage, https://github.com/theammir/presenturpy
Project-URL: Repository, https://github.com/theammir/presenturpy
Project-URL: Issues, https://github.com/theammir/presenturpy/issues
Keywords: present,presentation
Classifier: Development Status :: 7 - Inactive
Classifier: Environment :: Console
Classifier: Operating System :: OS Independent
Classifier: Programming Language :: Python :: 3 :: Only
Requires-Python: >=3.9
